cavity/__init__.py
cavity/core.py
cavity/helpers.py
cavity_py-0.1.0.dist-info/LICENSE
cavity_py-0.1.0.dist-info/METADATA
cavity_py-0.1.0.dist-info/WHEEL
cavity_py-0.1.0.dist-info/top_level.txt
cavity_py-0.1.0.dist-info/RECORD
