Metadata-Version: 2.1
Name: cavity-py
Version: 0.1.0
Summary: Python module for Solving Navier-Stokes equation in cavity geometry
Home-page: https://github.com/syoukera/cavity_py
Author: Akira Shioyoke
Author-email: s.akira2986@gmail.com
License: Copyright (c) 2017, Kenneth Reitz
Requires-Dist: numpy
Requires-Dist: matplotlib
